Metadata-Version: 2.0
Name: flake8-graphql
Version: 0.1.1
Summary: A flake8 plugin to lint your graphql queries
Home-page: https://github.com/michaelaquilina/flake8-graphql
Author: Michael Aquilina
Author-email: michaelaquilina@gmail.com
License: AGPLv3
Keywords: flake8,graphql
Platform: UNKNOWN
Classifier: Development Status :: 5 - Production/Stable
Classifier: Intended Audience :: Developers
Classifier: Natural Language :: English
Classifier: License :: OSI Approved :: GNU Affero General Public License v3 or later (AGPLv3+)
Classifier: Programming Language :: Python :: 3
Classifier: Programming Language :: Python :: 3.5
Classifier: Programming Language :: Python :: 3.6
Requires-Dist: flake8 (!=3.2.0,>=3)
Requires-Dist: graphql-core
